werkbank/.gitignore
werkbank/__init__.py
werkbank/mp.py
werkbank/nodes.py
werkbank/project.py
werkbank/rcsb.py
werkbank/server.py
werkbank/ui.py
werkbank/ui_types.py
werkbank/utils.py
werkbank/static/index.html
werkbank/static/assets/index-CIOU3o8r.js
werkbank/static/assets/index-D24c6_F0.css
werkbank-0.1.3.dist-info/METADATA
werkbank-0.1.3.dist-info/WHEEL
werkbank-0.1.3.dist-info/entry_points.txt
werkbank-0.1.3.dist-info/licenses/LICENSE
werkbank-0.1.3.dist-info/RECORD
