Metadata-Version: 2.4
Name: werkbank
Version: 0.1.3
Summary:  Model Context Protocol for Atomistic Simulations
License-File: LICENSE
Requires-Python: >=3.11
Requires-Dist: fastmcp>=2.12.0
Requires-Dist: flask>=3.1.2
Requires-Dist: znflow
Requires-Dist: zntrack>=0.8.9
